{
 "boba_version": 1,
 "days": 30,
 "seed": 20260710,
 "arms": [
  "static",
  "computed",
  "cart"
 ],
 "rent_per_day": 330,
 "cells": {
  "shock0_flex0.15": {
   "world": {
    "sigma_shock": 0.0,
    "flexible_share": 0.15
   },
   "margin": {
    "static": 45460.65,
    "computed": 45559.88,
    "cart": 54723.0
   },
   "totals": {
    "static": {
     "margin": 45460.65,
     "cups": 7567,
     "peak_balks": 830,
     "waste_cost": 219.0,
     "deferred": 0,
     "attach_rate": 0.861,
     "avg_peak_wait": 3.68,
     "consumer_surplus": 32619.0
    },
    "computed": {
     "margin": 45559.88,
     "cups": 7764,
     "peak_balks": 830,
     "waste_cost": 203.6,
     "deferred": 0,
     "attach_rate": 0.87,
     "avg_peak_wait": 3.68,
     "consumer_surplus": 33542.13
    },
    "cart": {
     "margin": 54723.0,
     "cups": 14814,
     "peak_balks": 643,
     "waste_cost": 94.6,
     "deferred": 2704,
     "attach_rate": 1.396,
     "avg_peak_wait": 4.29,
     "consumer_surplus": 46681.87
    }
   },
   "paired": {
    "computed_vs_static": {
     "margin": {
      "mean": 3.31,
      "ci95": [
       -5.5,
       12.12
      ],
      "n": 6,
      "block": 5
     },
     "consumer_surplus": {
      "mean": 30.77,
      "ci95": [
       26.77,
       34.77
      ],
      "n": 6,
      "block": 5
     },
     "peak_balks": {
      "mean": 0.0,
      "ci95": [
       0.0,
       0.0
      ],
      "n": 6,
      "block": 5
     },
     "waste_cost": {
      "mean": -0.51,
      "ci95": [
       -0.64,
       -0.38
      ],
      "n": 6,
      "block": 5
     },
     "toppings": {
      "mean": 7.93,
      "ci95": [
       5.88,
       9.99
      ],
      "n": 6,
      "block": 5
     },
     "deferred": {
      "mean": 0.0,
      "ci95": [
       0.0,
       0.0
      ],
      "n": 6,
      "block": 5
     }
    },
    "cart_vs_static": {
     "margin": {
      "mean": 308.75,
      "ci95": [
       289.81,
       327.68
      ],
      "n": 6,
      "block": 5
     },
     "consumer_surplus": {
      "mean": 468.76,
      "ci95": [
       452.47,
       485.05
      ],
      "n": 6,
      "block": 5
     },
     "peak_balks": {
      "mean": -6.23,
      "ci95": [
       -6.7,
       -5.77
      ],
      "n": 6,
      "block": 5
     },
     "waste_cost": {
      "mean": -4.15,
      "ci95": [
       -5.08,
       -3.21
      ],
      "n": 6,
      "block": 5
     },
     "toppings": {
      "mean": 472.17,
      "ci95": [
       454.33,
       490.0
      ],
      "n": 6,
      "block": 5
     },
     "deferred": {
      "mean": 90.13,
      "ci95": [
       86.56,
       93.71
      ],
      "n": 6,
      "block": 5
     }
    }
   }
  },
  "shock0_flex0.35": {
   "world": {
    "sigma_shock": 0.0,
    "flexible_share": 0.35
   },
   "margin": {
    "static": 45460.65,
    "computed": 45559.88,
    "cart": 55951.46
   },
   "totals": {
    "static": {
     "margin": 45460.65,
     "cups": 7567,
     "peak_balks": 830,
     "waste_cost": 219.0,
     "deferred": 0,
     "attach_rate": 0.861,
     "avg_peak_wait": 3.68,
     "consumer_surplus": 32619.0
    },
    "computed": {
     "margin": 45559.88,
     "cups": 7764,
     "peak_balks": 830,
     "waste_cost": 203.6,
     "deferred": 0,
     "attach_rate": 0.87,
     "avg_peak_wait": 3.68,
     "consumer_surplus": 33542.13
    },
    "cart": {
     "margin": 55951.46,
     "cups": 15122,
     "peak_balks": 632,
     "waste_cost": 97.0,
     "deferred": 3123,
     "attach_rate": 1.405,
     "avg_peak_wait": 4.24,
     "consumer_surplus": 47918.28
    }
   },
   "paired": {
    "computed_vs_static": {
     "margin": {
      "mean": 3.31,
      "ci95": [
       -5.5,
       12.12
      ],
      "n": 6,
      "block": 5
     },
     "consumer_surplus": {
      "mean": 30.77,
      "ci95": [
       26.77,
       34.77
      ],
      "n": 6,
      "block": 5
     },
     "peak_balks": {
      "mean": 0.0,
      "ci95": [
       0.0,
       0.0
      ],
      "n": 6,
      "block": 5
     },
     "waste_cost": {
      "mean": -0.51,
      "ci95": [
       -0.64,
       -0.38
      ],
      "n": 6,
      "block": 5
     },
     "toppings": {
      "mean": 7.93,
      "ci95": [
       5.88,
       9.99
      ],
      "n": 6,
      "block": 5
     },
     "deferred": {
      "mean": 0.0,
      "ci95": [
       0.0,
       0.0
      ],
      "n": 6,
      "block": 5
     }
    },
    "cart_vs_static": {
     "margin": {
      "mean": 349.69,
      "ci95": [
       331.99,
       367.39
      ],
      "n": 6,
      "block": 5
     },
     "consumer_surplus": {
      "mean": 509.98,
      "ci95": [
       495.68,
       524.27
      ],
      "n": 6,
      "block": 5
     },
     "peak_balks": {
      "mean": -6.6,
      "ci95": [
       -7.28,
       -5.92
      ],
      "n": 6,
      "block": 5
     },
     "waste_cost": {
      "mean": -4.07,
      "ci95": [
       -4.64,
       -3.49
      ],
      "n": 6,
      "block": 5
     },
     "toppings": {
      "mean": 491.2,
      "ci95": [
       478.16,
       504.24
      ],
      "n": 6,
      "block": 5
     },
     "deferred": {
      "mean": 104.1,
      "ci95": [
       100.98,
       107.22
      ],
      "n": 6,
      "block": 5
     }
    }
   }
  },
  "shock0.4_flex0.15": {
   "world": {
    "sigma_shock": 0.4,
    "flexible_share": 0.15
   },
   "margin": {
    "static": 48308.43,
    "computed": 48419.69,
    "cart": 56465.12
   },
   "totals": {
    "static": {
     "margin": 48308.43,
     "cups": 8044,
     "peak_balks": 1121,
     "waste_cost": 195.3,
     "deferred": 0,
     "attach_rate": 0.851,
     "avg_peak_wait": 4.4,
     "consumer_surplus": 34598.09
    },
    "computed": {
     "margin": 48419.69,
     "cups": 8268,
     "peak_balks": 1121,
     "waste_cost": 186.0,
     "deferred": 0,
     "attach_rate": 0.853,
     "avg_peak_wait": 4.4,
     "consumer_surplus": 35601.31
    },
    "cart": {
     "margin": 56465.12,
     "cups": 15391,
     "peak_balks": 931,
     "waste_cost": 98.0,
     "deferred": 3151,
     "attach_rate": 1.397,
     "avg_peak_wait": 4.87,
     "consumer_surplus": 48809.35
    }
   },
   "paired": {
    "computed_vs_static": {
     "margin": {
      "mean": 3.71,
      "ci95": [
       -6.28,
       13.69
      ],
      "n": 6,
      "block": 5
     },
     "consumer_surplus": {
      "mean": 33.44,
      "ci95": [
       25.69,
       41.19
      ],
      "n": 6,
      "block": 5
     },
     "peak_balks": {
      "mean": 0.0,
      "ci95": [
       0.0,
       0.0
      ],
      "n": 6,
      "block": 5
     },
     "waste_cost": {
      "mean": -0.31,
      "ci95": [
       -0.68,
       0.06
      ],
      "n": 6,
      "block": 5
     },
     "toppings": {
      "mean": 6.93,
      "ci95": [
       5.31,
       8.55
      ],
      "n": 6,
      "block": 5
     },
     "deferred": {
      "mean": 0.0,
      "ci95": [
       0.0,
       0.0
      ],
      "n": 6,
      "block": 5
     }
    },
    "cart_vs_static": {
     "margin": {
      "mean": 271.89,
      "ci95": [
       214.0,
       329.78
      ],
      "n": 6,
      "block": 5
     },
     "consumer_surplus": {
      "mean": 473.71,
      "ci95": [
       388.03,
       559.39
      ],
      "n": 6,
      "block": 5
     },
     "peak_balks": {
      "mean": -6.33,
      "ci95": [
       -8.01,
       -4.66
      ],
      "n": 6,
      "block": 5
     },
     "waste_cost": {
      "mean": -3.24,
      "ci95": [
       -4.25,
       -2.24
      ],
      "n": 6,
      "block": 5
     },
     "toppings": {
      "mean": 488.57,
      "ci95": [
       421.75,
       555.38
      ],
      "n": 6,
      "block": 5
     },
     "deferred": {
      "mean": 105.03,
      "ci95": [
       78.73,
       131.33
      ],
      "n": 6,
      "block": 5
     }
    }
   }
  },
  "shock0.4_flex0.35": {
   "world": {
    "sigma_shock": 0.4,
    "flexible_share": 0.35
   },
   "margin": {
    "static": 48308.43,
    "computed": 48419.69,
    "cart": 57641.24
   },
   "totals": {
    "static": {
     "margin": 48308.43,
     "cups": 8044,
     "peak_balks": 1121,
     "waste_cost": 195.3,
     "deferred": 0,
     "attach_rate": 0.851,
     "avg_peak_wait": 4.4,
     "consumer_surplus": 34598.09
    },
    "computed": {
     "margin": 48419.69,
     "cups": 8268,
     "peak_balks": 1121,
     "waste_cost": 186.0,
     "deferred": 0,
     "attach_rate": 0.853,
     "avg_peak_wait": 4.4,
     "consumer_surplus": 35601.31
    },
    "cart": {
     "margin": 57641.24,
     "cups": 15651,
     "peak_balks": 940,
     "waste_cost": 102.3,
     "deferred": 3556,
     "attach_rate": 1.404,
     "avg_peak_wait": 4.82,
     "consumer_surplus": 49980.27
    }
   },
   "paired": {
    "computed_vs_static": {
     "margin": {
      "mean": 3.71,
      "ci95": [
       -6.28,
       13.69
      ],
      "n": 6,
      "block": 5
     },
     "consumer_surplus": {
      "mean": 33.44,
      "ci95": [
       25.69,
       41.19
      ],
      "n": 6,
      "block": 5
     },
     "peak_balks": {
      "mean": 0.0,
      "ci95": [
       0.0,
       0.0
      ],
      "n": 6,
      "block": 5
     },
     "waste_cost": {
      "mean": -0.31,
      "ci95": [
       -0.68,
       0.06
      ],
      "n": 6,
      "block": 5
     },
     "toppings": {
      "mean": 6.93,
      "ci95": [
       5.31,
       8.55
      ],
      "n": 6,
      "block": 5
     },
     "deferred": {
      "mean": 0.0,
      "ci95": [
       0.0,
       0.0
      ],
      "n": 6,
      "block": 5
     }
    },
    "cart_vs_static": {
     "margin": {
      "mean": 311.09,
      "ci95": [
       250.9,
       371.29
      ],
      "n": 6,
      "block": 5
     },
     "consumer_surplus": {
      "mean": 512.74,
      "ci95": [
       427.92,
       597.56
      ],
      "n": 6,
      "block": 5
     },
     "peak_balks": {
      "mean": -6.03,
      "ci95": [
       -7.26,
       -4.81
      ],
      "n": 6,
      "block": 5
     },
     "waste_cost": {
      "mean": -3.1,
      "ci95": [
       -4.05,
       -2.15
      ],
      "n": 6,
      "block": 5
     },
     "toppings": {
      "mean": 504.07,
      "ci95": [
       435.17,
       572.97
      ],
      "n": 6,
      "block": 5
     },
     "deferred": {
      "mean": 118.53,
      "ci95": [
       91.19,
       145.88
      ],
      "n": 6,
      "block": 5
     }
    }
   }
  }
 }
}