{
  "schema": "block.week.v1",
  "meta": {
    "generated": "2026-07-10",
    "badge": "canned preview — live sim wiring coming",
    "provenance": "Numbers are a HAND-AUTHORED preview, deliberately conservative (single-digit-to-tens of $/day per venue). Live wiring replaces this file with block/runner.py output on the same schema. Published 30-day twin (block/RESULTS-B1B2.md) ran an aggressive scenario with larger per-venue deltas; this preview stays modest on purpose.",
    "day_seconds": 6,
    "days": 7,
    "day_start_hour": 5.0,
    "worlds": ["sticker", "snhp"],
    "hud_labels": { "shopper": "shoppers kept", "merchant": "merchants earned" }
  },

  "venues": [
    { "id": "vending",  "slot": 0, "label": "VEND",   "kind": "machine" },
    { "id": "bodega",   "slot": 1, "label": "BODEGA", "kind": "deli" },
    { "id": "boba",     "slot": 2, "label": "BOBA",   "kind": "boba" },
    { "id": "bakery",   "slot": 3, "label": "BAKERY", "kind": "bakery" },
    { "id": "flower",   "slot": 4, "label": "FLOWER", "kind": "flower" },
    { "id": "barber",   "slot": 5, "label": "BARBER", "kind": "barber" },
    { "id": "fashion",  "slot": 6, "label": "FASHION","kind": "fashion" },
    { "id": "vintage",  "slot": 7, "label": "VINTAGE","kind": "vintage" },
    { "id": "bar",      "slot": 8, "label": "BAR",    "kind": "bar" },
    { "id": "parking",  "slot": 9, "label": "PARK",   "kind": "parking" }
  ],

  "regulars": [
    { "id": "maria", "name": "Maria",  "persona": "local",         "home": "bodega",
      "look": { "skin": "tan",  "hair": "gray",  "top": "#b0463c", "bottom": "#3a3550", "prop": "tote",     "hat": "scarf" },
      "churn": { "sticker_lastday": 3, "reason": "anchor hike at the bodega" } },
    { "id": "deb",   "name": "Deb",    "persona": "office-worker", "home": "vending",
      "look": { "skin": "tan",  "hair": "brown", "top": "#2e5a8a", "bottom": "#232a3a", "prop": "coffee",   "hat": "none" },
      "churn": { "sticker_lastday": 5, "reason": "machine anchor creep" } },
    { "id": "sam",   "name": "Sam",    "persona": "student",       "home": "boba",
      "look": { "skin": "brown","hair": "black", "top": "#3a8a62", "bottom": "#2a2438", "prop": "backpack", "hat": "phones" },
      "churn": { "sticker_lastday": 4, "reason": "boba queue balk at peak" } },
    { "id": "theo",  "name": "Theo",   "persona": "office-worker", "home": "bakery",
      "look": { "skin": "pale", "hair": "sandy", "top": "#7a6a3a", "bottom": "#2b2338", "prop": "satchel",  "hat": "none" },
      "churn": { "sticker_lastday": 6, "reason": "stale day-old shelf" } },
    { "id": "rosa",  "name": "Rosa",   "persona": "local",         "home": "flower",
      "look": { "skin": "tan",  "hair": "white", "top": "#8a5aa0", "bottom": "#3a3550", "prop": "cane",     "hat": "none" },
      "churn": { "sticker_lastday": 4, "reason": "wilted buckets, no deal" } },
    { "id": "kwame", "name": "Kwame",  "persona": "office-worker", "home": "barber",
      "look": { "skin": "brown","hair": "black", "top": "#c07a2a", "bottom": "#2b2338", "prop": "none",     "hat": "cap" },
      "churn": { "sticker_lastday": 5, "reason": "flat slot pricing" } },
    { "id": "yuki",  "name": "Yuki",   "persona": "student",       "home": "fashion",
      "look": { "skin": "pale", "hair": "black", "top": "#c05a8a", "bottom": "#2a2438", "prop": "shopbag",  "hat": "beanie" },
      "churn": { "sticker_lastday": 6, "reason": "−70% clearance dread" } },
    { "id": "lou",   "name": "Big Lou","persona": "local",         "home": "bar",
      "look": { "skin": "tan",  "hair": "bald",  "top": "#3a4a8a", "bottom": "#2b2338", "prop": "none",     "hat": "none", "big": true },
      "churn": { "sticker_lastday": 6, "reason": "happy hour cut short" } }
  ],

  "ledger": {
    "day_weight": [0.03, 0.28, 0.55, 0.75, 0.80, 0.95, 1.00],
    "day_weight_note": "day d's whole contribution = per-venue mature delta * day_weight[d]. day0 ≈ 0: the two blocks START IDENTICAL and diverge.",
    "per_venue_mature": {
      "vending": { "merchant": 4,  "shopper": 7,  "src": "RESULTS-B1B2 vending +3.01/+7.14" },
      "bodega":  { "merchant": 9,  "shopper": 14, "src": "RESULTS-B1B2 bodega adopt row, scaled to preview" },
      "boba":    { "merchant": 24, "shopper": 40, "src": "RESULTS-B1B2 boba +336/+496, held to tens for preview" },
      "bakery":  { "merchant": 12, "shopper": 18, "src": "candidate — day-old markdown wedge (DESIGN 4c)" },
      "flower":  { "merchant": 8,  "shopper": 12, "src": "candidate — perishability + event spikes" },
      "barber":  { "merchant": 6,  "shopper": 9,  "src": "candidate — slot pricing, no inventory" },
      "fashion": { "merchant": 20, "shopper": 38, "src": "RESULTS-B1B2 fashion +396 (mostly timing), held to tens" },
      "vintage": { "merchant": 7,  "shopper": 14, "src": "candidate — make-an-offer, one-of-one" },
      "bar":     { "merchant": 12, "shopper": 16, "src": "candidate — computed happy hour" },
      "parking": { "merchant": 16, "shopper": 20, "src": "candidate — yield mgmt, duration bundles" }
    },
    "block_mature": { "merchant": 118, "shopper": 188 },
    "week_total_note": "Cumulative HUD after the full week: merchants ≈ $514, shoppers ≈ $819 (sum of mature * day_weight over 7 days)."
  },

  "crowd": {
    "seed": 20260710,
    "ambient_concurrent": {
      "sticker": [15, 15, 14, 12, 10, 8, 7],
      "snhp":    [15, 15, 16, 17, 17, 18, 18]
    },
    "hour_weight_note": "intraday crowd multiplier by clock hour (0-23), applied to ambient_concurrent",
    "hour_weight": [0.05,0.03,0.02,0.02,0.03,0.08,0.20,0.45,0.85,0.75,0.65,0.70,0.95,0.90,0.72,0.68,0.80,0.98,0.95,0.82,0.66,0.48,0.30,0.14],
    "receipt_rate_per_hour_snhp": 5.0,
    "receipt_pool": {
      "vending":  [ ["2x cola −$1.40 · combo", 1.40], ["water −$0.60", 0.60], ["snack pair −$0.90", 0.90] ],
      "bodega":   [ ["2x sandwich −$2.10 · tonight", 2.10], ["chopped cheese −$1.80", 1.80], ["BEC + coffee −$1.25", 1.25] ],
      "boba":     [ ["pickup 4:15 −$1.35", 1.35], ["milk tea + pearls −$1.10", 1.10], ["off-peak −$1.60", 1.60] ],
      "bakery":   [ ["day-old box −$3.20 · 6pm", 3.20], ["croissant 2-for −$1.50", 1.50], ["loaf −$1.80", 1.80] ],
      "flower":   [ ["bouquet −$5.00 · closing", 5.00], ["stems −$2.20", 2.20], ["event lot −$4.00", 4.00] ],
      "barber":   [ ["cut+beard slot −$4.00", 4.00], ["quiet-hour −$3.00", 3.00], ["walk-in −$2.50", 2.50] ],
      "fashion":  [ ["hoodie −$14 · end-season", 14.0], ["tee 2-for −$8", 8.0], ["slip dress −$18", 18.0] ],
      "vintage":  [ ["denim offer −$9", 9.0], ["jacket −$12 · as-is", 12.0], ["record −$3", 3.0] ],
      "bar":      [ ["happy hour pint −$2.00", 2.00], ["round of 4 −$5", 5.0], ["late slot −$3", 3.0] ],
      "parking":  [ ["2h bundle −$6", 6.0], ["early-bird −$8", 8.0], ["evening flat −$4", 4.0] ]
    }
  },

  "mood": {
    "gray_note": "sticker block desaturation 0-1 by day (churn as depopulation, the divergence-as-drama). snhp stays warm (0).",
    "gray": {
      "sticker": [0.00, 0.06, 0.14, 0.24, 0.34, 0.46, 0.58],
      "snhp":    [0.00, 0.00, 0.00, 0.00, 0.00, 0.00, 0.00]
    }
  },

  "decay": {
    "note": "per-venue sticker-block decay 0-1 by day — drives spoilage bins, clearance racks, fading flowers, dimmed neon. snhp venues stay at 0.",
    "sticker": {
      "vending": [0,0,0.05,0.15,0.25,0.40,0.55],
      "bodega":  [0,0,0.10,0.25,0.40,0.55,0.70],
      "boba":    [0,0,0.10,0.30,0.45,0.60,0.75],
      "bakery":  [0,0,0.15,0.30,0.45,0.62,0.80],
      "flower":  [0,0.05,0.20,0.38,0.55,0.72,0.90],
      "barber":  [0,0,0.05,0.12,0.22,0.35,0.50],
      "fashion": [0,0,0.12,0.28,0.45,0.66,0.85],
      "vintage": [0,0,0.08,0.18,0.30,0.45,0.60],
      "bar":     [0,0,0.10,0.22,0.35,0.50,0.68],
      "parking": [0,0,0.05,0.14,0.25,0.38,0.52]
    }
  },

  "weather": ["clear", "clear", "clear", "clear", "rain", "clear", "overcast"],

  "beats": [
    { "day": 0, "hour": 6.0, "world": "snhp",    "type": "truck", "venue": "bodega", "shared_with": "bakery", "supplier": "deli-produce", "negotiated": true },
    { "day": 0, "hour": 6.4, "world": "snhp",    "type": "truck", "venue": "boba",   "shared_with": "bar",    "supplier": "beverage",     "negotiated": true },
    { "day": 0, "hour": 5.7, "world": "sticker", "type": "truck", "venue": "bodega", "supplier": "deli-produce", "negotiated": false },
    { "day": 0, "hour": 6.9, "world": "sticker", "type": "truck", "venue": "bakery", "supplier": "deli-produce", "negotiated": false },
    { "day": 0, "hour": 7.6, "world": "sticker", "type": "truck", "venue": "boba",   "supplier": "beverage",     "negotiated": false },
    { "day": 0, "hour": 8.2, "world": "sticker", "type": "truck", "venue": "bar",    "supplier": "beverage",     "negotiated": false },

    { "day": 1, "hour": 6.1, "world": "snhp",    "type": "truck", "venue": "flower", "shared_with": "fashion", "supplier": "florist-route", "negotiated": true },
    { "day": 1, "hour": 6.5, "world": "snhp",    "type": "truck", "venue": "bodega", "shared_with": "bakery",  "supplier": "deli-produce",  "negotiated": true },
    { "day": 1, "hour": 6.0, "world": "sticker", "type": "truck", "venue": "flower", "supplier": "florist-route", "negotiated": false },
    { "day": 1, "hour": 7.3, "world": "sticker", "type": "truck", "venue": "bodega", "supplier": "deli-produce",  "negotiated": false },

    { "day": 2, "hour": 6.2, "world": "snhp",    "type": "truck", "venue": "bodega", "shared_with": "bakery", "supplier": "deli-produce", "negotiated": true },
    { "day": 2, "hour": 6.6, "world": "snhp",    "type": "truck", "venue": "boba",   "shared_with": "bar",    "supplier": "beverage",     "negotiated": true },
    { "day": 2, "hour": 5.8, "world": "sticker", "type": "truck", "venue": "bakery", "supplier": "deli-produce", "negotiated": false },
    { "day": 2, "hour": 9.4, "world": "sticker", "type": "spoil", "venue": "bodega", "kind": "bin" },
    { "day": 2, "hour": 18.6,"world": "sticker", "type": "spoil", "venue": "bakery", "kind": "bin" },

    { "day": 3, "hour": 6.0, "world": "snhp",    "type": "truck", "venue": "bodega", "shared_with": "bakery",  "supplier": "deli-produce",  "negotiated": true },
    { "day": 3, "hour": 6.4, "world": "snhp",    "type": "truck", "venue": "flower", "shared_with": "fashion", "supplier": "florist-route", "negotiated": true },
    { "day": 3, "hour": 5.6, "world": "sticker", "type": "truck", "venue": "bodega", "supplier": "deli-produce",  "negotiated": false },
    { "day": 3, "hour": 6.7, "world": "sticker", "type": "truck", "venue": "flower", "supplier": "florist-route", "negotiated": false },
    { "day": 3, "hour": 9.5, "world": "sticker", "type": "churn", "regular": "maria", "venue": "bodega", "reason": "anchor hike" },
    { "day": 3, "hour": 13.2,"world": "sticker", "type": "clearance", "venue": "fashion", "pct": 40 },

    { "day": 4, "hour": 6.3, "world": "snhp",    "type": "truck", "venue": "boba",   "shared_with": "bar",    "supplier": "beverage",     "negotiated": true },
    { "day": 4, "hour": 6.8, "world": "snhp",    "type": "truck", "venue": "bodega", "shared_with": "bakery", "supplier": "deli-produce", "negotiated": true },
    { "day": 4, "hour": 7.1, "world": "sticker", "type": "truck", "venue": "boba",   "supplier": "beverage", "negotiated": false },
    { "day": 4, "hour": 15.0,"world": "sticker", "type": "churn", "regular": "sam",  "venue": "boba",   "reason": "queue balk" },
    { "day": 4, "hour": 11.0,"world": "sticker", "type": "churn", "regular": "rosa", "venue": "flower", "reason": "wilted, no deal" },
    { "day": 4, "hour": 14.0,"world": "sticker", "type": "clearance", "venue": "fashion", "pct": 55 },

    { "day": 5, "hour": 6.1, "world": "snhp",    "type": "truck", "venue": "bodega", "shared_with": "bakery",  "supplier": "deli-produce",  "negotiated": true },
    { "day": 5, "hour": 6.5, "world": "snhp",    "type": "truck", "venue": "flower", "shared_with": "fashion", "supplier": "florist-route", "negotiated": true },
    { "day": 5, "hour": 5.9, "world": "sticker", "type": "truck", "venue": "bakery", "supplier": "deli-produce", "negotiated": false },
    { "day": 5, "hour": 8.5, "world": "sticker", "type": "churn", "regular": "deb",   "venue": "vending", "reason": "anchor creep" },
    { "day": 5, "hour": 17.5,"world": "sticker", "type": "churn", "regular": "kwame", "venue": "barber",  "reason": "flat slots" },
    { "day": 5, "hour": 18.4,"world": "sticker", "type": "clearance", "venue": "fashion", "pct": 70 },

    { "day": 6, "hour": 6.2, "world": "snhp",    "type": "truck", "venue": "bodega", "shared_with": "bakery", "supplier": "deli-produce", "negotiated": true },
    { "day": 6, "hour": 6.6, "world": "snhp",    "type": "truck", "venue": "boba",   "shared_with": "bar",    "supplier": "beverage",     "negotiated": true },
    { "day": 6, "hour": 6.0, "world": "sticker", "type": "truck", "venue": "bodega", "supplier": "deli-produce", "negotiated": false },
    { "day": 6, "hour": 12.0,"world": "sticker", "type": "churn", "regular": "theo", "venue": "bakery", "reason": "stale shelf" },
    { "day": 6, "hour": 19.5,"world": "sticker", "type": "churn", "regular": "lou",  "venue": "bar",    "reason": "happy hour cut" },
    { "day": 6, "hour": 20.5,"world": "sticker", "type": "churn", "regular": "yuki", "venue": "fashion","reason": "clearance dread" }
  ]
}
